spharm.py
_spherepack.cpython-310-x86_64-linux-gnu.so
__init__.py
pyspharm_syl-1.2.1.dist-info/WHEEL
pyspharm_syl-1.2.1.dist-info/METADATA
pyspharm_syl-1.2.1.dist-info/LICENSE.spherepack
pyspharm_syl-1.2.1.dist-info/RECORD
pyspharm_syl.libs/libsvml-af2309bc.so
pyspharm_syl.libs/libintlc-1de73b2d.so.5
pyspharm_syl.libs/libimf-53ff2c4b.so
