Metadata-Version: 2.1
Name: pyspharm-syl
Version: 1.2.1
Summary: Python Spherical Harmonic Transform Module
Home-page: https://github.com/shenyulu/pyspharm-syl
Author: shenyulu
License: PLEASE READ THIS SOFTWARE LICENSE ("LICENSE") CAREFULLY. 
Classifier: Programming Language :: Python
Classifier: Programming Language :: Python :: 3
Classifier: Programming Language :: Python :: 3.9
Classifier: Programming Language :: Python :: 3.10
Classifier: Programming Language :: Python :: 3.11
Classifier: Programming Language :: Python :: 3.12
Classifier: Programming Language :: Python :: 3 :: Only
Classifier: Topic :: Scientific/Engineering
Classifier: Operating System :: Microsoft :: Windows
Classifier: Operating System :: POSIX
Classifier: Operating System :: Unix
Classifier: Operating System :: MacOS
Project-URL: Homepage, https://github.com/shenyulu/pyspharm-syl
Project-URL: Documentation, https://github.com/shenyulu/pyspharm-syl
Project-URL: Source, https://github.com/shenyulu/pyspharm-syl
Project-URL: Download, https://pypi.org/project/pyspharm-syl/#files
Project-URL: Tracker, https://github.com/shenyulu/pyspharm-syl/issues
Requires-Python: >=3.9
Requires-Dist: numpy>=1.24.3
Requires-Dist: intel-fortran-rt
Requires-Dist: dpcpp-cpp-rt
